{
  "$schema": "https://mintlify.com/docs.json",
  "theme": "mint",
  "name": "LandingAI",
  "colors": {
    "primary": "#16A34A",
    "light": "#07C983",
    "dark": "#15803D"
  },
  "favicon": "/favicon_landing-ai.svg",
  "navigation": {
    "dropdowns": [
      {
        "dropdown": "LandingLens",
        "icon": "book-open",
        "tabs": [
          {
            "tab": "Guides",
            "groups": [
              {
                "group": "Get Started",
                "pages": [
                  "get-started/landinglens-get-started",
                  "introduction",
                  "quickstart",
                  "development"
                ]
              },
              {
                "group": "Image Capture Best Practices",
                "pages": [
                  "image-capture-best-practices/image-capture-best-practices"
                ]
              },
              {
                "group": "Upload Images",
                "pages": [
                  "upload-images/upload-images"
                ]
              },
              {
                "group": "Essentials",
                "pages": [
                  "essentials/md_test",
                  "essentials/python_readme",
                  "essentials/test",
                  "essentials/markdown-test",
                  "essentials/code",
                  "essentials/images",
                  "essentials/settings",
                  "essentials/navigation",
                  "essentials/reusable-snippets"
                ]
              }
            ]
          },
          {
            "tab": "API Reference",
            "groups": [
              {
                "group": "API Documentation",
                "pages": [
                  "api-reference/introduction"
                ]
              },
              {
                "group": "Endpoint Examples",
                "pages": [
                  "api-reference/endpoint/get",
                  "api-reference/endpoint/create",
                  "api-reference/endpoint/delete",
                  "api-reference/endpoint/webhook"
                ]
              }
            ]
          },
          {
            "tab": "LandingLens API",
            "openapi": "landinglens-api/document.json"
          }
        ]
      },
      {
        "dropdown": "VisionAgent",
        "icon": "sqaure-terminal",
        "pages": [
          "essentials/md_test",
          "essentials/python_readme"
        ]
      }
    ]
  },
  "logo": {
    "light": "/logo/LandingAI-logo-primary-color-RGB.svg",
    "dark": "/logo/LandingAI-logo-primary-color-RGB.svg"
  },
  "navbar": {
    "links": [
      {
        "label": "Support",
        "href": "mailto:support@landing.ai"
      }
    ],
    "primary": {
      "type": "button",
      "label": "Dashboard",
      "href": "https://dashboard.mintlify.com"
    }
  },
  "footer": {
    "socials": {
      "x": "https://twitter.com/landingAI",
      "github": "https://github.com/landing-ai",
      "linkedin": "https://www.linkedin.com/company/landing-ai/"
    }
  },
  "redirects": [
    {
      "source": "essentials/markdown",
      "destination": "essentials/markdown-test"
    }
  ]
}